bout_install/Installer.py
bout_install/InstallerUsingCMake.py
bout_install/InstallerUsingGit.py
bout_install/__init__.py
bout_install/__main__.py
bout_install/config.ini
bout_install/main.py
bout_install/cmake_installer/SundialsInstaller.py
bout_install/cmake_installer/__init__.py
bout_install/git_installer/BOUTPPInstaller.py
bout_install/git_installer/__init__.py
bout_install/installer/CMakeInstaller.py
bout_install/installer/FFMPEGInstaller.py
bout_install/installer/FFTWInstaller.py
bout_install/installer/GCCInstaller.py
bout_install/installer/HDF5Installer.py
bout_install/installer/MPIInstaller.py
bout_install/installer/NetCDFInstaller.py
bout_install/installer/PETScInstaller.py
bout_install/installer/SLEPcInstaller.py
bout_install/installer/__init__.py
tests/__init__.py
tests/utils.py
tests/bout_install/__init__.py
tests/bout_install/test_installer.py
tests/bout_install/test_main.py
tests/bout_install/cmake_installer/__init__.py
tests/bout_install/installer/__init__.py
bout_install-0.1.9.dist-info/LICENSE
bout_install-0.1.9.dist-info/METADATA
bout_install-0.1.9.dist-info/WHEEL
bout_install-0.1.9.dist-info/entry_points.txt
bout_install-0.1.9.dist-info/top_level.txt
bout_install-0.1.9.dist-info/RECORD
