Metadata-Version: 2.1
Name: bout-install
Version: 0.1.9
Summary: Python package to install BOUT++ and its dependencies
Home-page: https://github.com/CELMA-project/bout_install
Author: Michael Løiten
Author-email: michael.l.magnussen@gmail.com
License: UNKNOWN
Keywords: bout++,bout,installation,plasma,turbulence
Platform: UNKNOWN
Classifier: Programming Language :: Python :: 3
Classifier: License :: OSI Approved :: GNU Lesser General Public License v3 or later (LGPLv3+)
Classifier: Operating System :: OS Independent
Requires-Dist: requests (>=2.20.1)
